f021/__init__.py
f021/hiapi.py
f021/api_plus/__init__.py
f021-0.0.2.dist-info/LICENSE
f021-0.0.2.dist-info/METADATA
f021-0.0.2.dist-info/WHEEL
f021-0.0.2.dist-info/top_level.txt
f021-0.0.2.dist-info/RECORD
