Metadata-Version: 2.1
Name: f021
Version: 0.0.2
Summary: 网站 f021.top 的帮助库
Home-page: https://github.com/Hifive55555/f021-api
Author: Hifive
Author-email: 2019912635@qq.com
Classifier: Programming Language :: Python :: 3
Classifier: License :: OSI Approved :: MIT License
Classifier: Operating System :: OS Independent
License-File: LICENSE
